{
    "pizza": [
        {
            "name": "Margherita Pizza",
            "price": 19.25,
            "rating": 4.3
        },
        {
            "name": "Pepperoni Pizza",
            "price": 12.99,
            "rating": 4.7
        },
        {
            "name": "Hawaiian Pizza",
            "price": 18.99,
            "rating": 4.1
        },
        {
            "name": "Four Cheese Pizza",
            "price": 25.5,
            "rating": 4.8
        },
        {
            "name": "Vegetarian Pizza",
            "price": 20.0,
            "rating": 4.4
        },
        {
            "name": "BBQ Chicken Pizza",
            "price": 19.5,
            "rating": 4.6
        }
    ],
    "burgers": [
        {
            "name": "Classic Cheeseburger",
            "price": 12.25,
            "rating": 4.2
        },
        {
            "name": "Double Cheeseburger",
            "price": 17.99,
            "rating": 4.5
        },
        {
            "name": "Mushroom Swiss Burger",
            "price": 19.99,
            "rating": 4.3
        },
        {
            "name": "Veggie Burger",
            "price": 30.5,
            "rating": 4.6
        },
        {
            "name": "Chicken Burger",
            "price": 28.5,
            "rating": 4.4
        },
        {
            "name": "Truffle Burger",
            "price": 29.5,
            "rating": 4.7
        }
    ],
    "sandwiches": [
        {
            "name": "Turkey & Swiss",
            "price": 10.25,
            "rating": 4.3
        },
        {
            "name": "Ham & Cheddar",
            "price": 9.99,
            "rating": 4.2
        },
        {
            "name": "Grilled Cheese",
            "price": 10.99,
            "rating": 4.4
        },
        {
            "name": "Chicken Avocado",
            "price": 14.5,
            "rating": 4.5
        },
        {
            "name": "Caprese",
            "price": 15.0,
            "rating": 4.3
        }
    ],
    "salads": [
        {
            "name": "Caesar Salad",
            "price": 12.25,
            "rating": 3.9
        },
        {
            "name": "Greek Salad",
            "price": 17.99,
            "rating": 4.4
        },
        {
            "name": "House Salad",
            "price": 19.99,
            "rating": 4.3
        },
        {
            "name": "Cobb Salad",
            "price": 30.5,
            "rating": 5
        },
        {
            "name": "Southwest Salad",
            "price": 28.5,
            "rating": 4.5
        }
    ],
    "juices": [
        {
            "name": "Fresh Orange Juice",
            "price": 12.25,
            "rating": 4.5
        },
        {
            "name": "Apple Juice",
            "price": 17.99,
            "rating": 4.3
        },
        {
            "name": "Carrot Juice",
            "price": 19.99,
            "rating": 4.2
        },
        {
            "name": "Pineapple Juice",
            "price": 30.5,
            "rating": 4.6
        }
    ],
    "french fries": [
        {
            "name": "Original Salted Fries",
            "price": 12.25,
            "rating": 5
        },
        {
            "name": "Sweet Potato Fries",
            "price": 17.99,
            "rating": 4.5
        },
        {
            "name": "Crinkle-Cut Fries",
            "price": 19.99,
            "rating": 4.3
        },
        {
            "name": "Curly Fries",
            "price": 30.5,
            "rating": 4.6
        },
        {
            "name": "Cheese Fries",
            "price": 30.5,
            "rating": 4.7
        }
    ],
    "desserts": [
        {
            "name": "Chocolate Fondant",
            "price": 0.625,
            "rating": 4.4
        },
        {
            "name": "Tiramisu",
            "price": 7.99,
            "rating": 5
        },
        {
            "name": "Baklava",
            "price": 12.99,
            "rating": 4.5
        },
        {
            "name": "Crème Brûlée",
            "price": 13.5,
            "rating": 4.6
        },
        {
            "name": "Fruit Tart",
            "price": 15.5,
            "rating": 4.2
        },
        {
            "name": "Cheesecake",
            "price": 5.5,
            "rating": 4.3
        }
    ]
}
